{"cameraMode":{"drawMode":0,"name":"Shaded","section":"Shading Mode"},"sceneLighting":true,"audioPlay":false,"sceneViewState":{"m_AlwaysRefresh":false,"showFog":true,"showSkybox":true,"showFlares":true,"showImageEffects":true,"showParticleSystems":true,"showVisualEffectGraphs":true,"m_FxEnabled":true},"in2DMode":false,"pivot":{"x":483.5,"y":272.0,"z":0.0},"rotation":{"x":0.1296061873435974,"y":-0.4053233563899994,"z":0.058073852211236957,"w":0.9031271934509277},"size":554.7578125,"orthographic":true}